LICENSE.md
README.md
setup.cfg
setup.py
openai_summarizer/__init__.py
openai_summarizer/email_summarizer.py
openai_summarizer.egg-info/PKG-INFO
openai_summarizer.egg-info/SOURCES.txt
openai_summarizer.egg-info/dependency_links.txt
openai_summarizer.egg-info/entry_points.txt
openai_summarizer.egg-info/requires.txt
openai_summarizer.egg-info/top_level.txt
openai_summarizer.egg-info/zip-safe