Metadata-Version: 2.1
Name: openai-summarizer
Version: 0.1.6
Summary: Summarize text using OpenAI.
Home-page: https://www.github.com/aalekhpatel07/openai-summarizer
Author: Aalekh Patel
Author-email: hi@aalekhpatel.com
License: MIT
Keywords: openai summarizer email text
Platform: UNKNOWN
License-File: LICENSE.md
